iMeshDashboard/__init__.py
iMeshDashboard/__main__.py
iMeshDashboard/iMesh-dashboard.py
iMesh_Dashboard-0.2.14.data/data/iMeshDashboard/conf/app.conf.example
iMesh_Dashboard-0.2.14.data/data/iMeshDashboard/css/bootstrap.min.css
iMesh_Dashboard-0.2.14.data/data/iMeshDashboard/css/bootstrap.min.css.map
iMesh_Dashboard-0.2.14.data/data/iMeshDashboard/img/iMesh.png
iMesh_Dashboard-0.2.14.data/data/iMeshDashboard/img/iMeshLight.png
iMesh_Dashboard-0.2.14.data/data/iMeshDashboard/js/bootstrap.bundle.min.js
iMesh_Dashboard-0.2.14.data/data/iMeshDashboard/js/bootstrap.bundle.min.js.map
iMesh_Dashboard-0.2.14.data/data/iMeshDashboard/js/jquery-3.6.0.min.js
iMesh_Dashboard-0.2.14.data/data/iMeshDashboard/service/iMeshDashboard.service
iMesh_Dashboard-0.2.14.data/data/iMeshDashboard/service/iMeshDashboardServiceInstall.sh
iMesh_Dashboard-0.2.14.data/data/iMeshDashboard/templates/base.html
iMesh_Dashboard-0.2.14.data/data/iMeshDashboard/templates/config.html
iMesh_Dashboard-0.2.14.data/data/iMeshDashboard/templates/index.html
iMesh_Dashboard-0.2.14.data/data/iMeshDashboard/templates/lh.html
iMesh_Dashboard-0.2.14.data/data/iMeshDashboard/templates/map.html
iMesh_Dashboard-0.2.14.dist-info/LICENSE
iMesh_Dashboard-0.2.14.dist-info/METADATA
iMesh_Dashboard-0.2.14.dist-info/WHEEL
iMesh_Dashboard-0.2.14.dist-info/entry_points.txt
iMesh_Dashboard-0.2.14.dist-info/top_level.txt
iMesh_Dashboard-0.2.14.dist-info/RECORD
