Metadata-Version: 2.1
Name: iMesh-Dashboard
Version: 0.2.14
Summary: Create Dashboard for serial connected meshtastic device
Home-page: https://github.com/iz1kga/Meshtastic-rpi-dashboard
Author: iz1kga
Author-email: iz1kga@gmail.com
License: apache 2.0
Platform: UNKNOWN
Classifier: Programming Language :: Python :: 3
Classifier: License :: OSI Approved :: MIT License
Classifier: Operating System :: OS Independent
Requires-Python: >=3.6
Requires-Dist: Flask-APScheduler (==1.11.0)
Requires-Dist: Flask-BasicAuth (==0.2.0)
Requires-Dist: Flask (==1.1.2)
Requires-Dist: configparser (>=5.0.1)
Requires-Dist: meshtastic (>=1.2.30)
Requires-Dist: paho-mqtt (==1.5.1)
Requires-Dist: timeago (>=1.0.15)
Requires-Dist: waitress (==1.4.4)
